scheduler/__init__.py
scheduler/apps.py
scheduler/decorators.py
scheduler/py.typed
scheduler/settings.py
scheduler/urls.py
scheduler/admin/__init__.py
scheduler/admin/ephemeral_models.py
scheduler/admin/task_admin.py
scheduler/helpers/__init__.py
scheduler/helpers/callback.py
scheduler/helpers/sentry_integration.py
scheduler/helpers/timeouts.py
scheduler/helpers/utils.py
scheduler/helpers/queues/__init__.py
scheduler/helpers/queues/getters.py
scheduler/helpers/queues/queue_logic.py
scheduler/management/__init__.py
scheduler/management/commands/__init__.py
scheduler/management/commands/delete_failed_executions.py
scheduler/management/commands/export.py
scheduler/management/commands/import.py
scheduler/management/commands/run_job.py
scheduler/management/commands/scheduler_stats.py
scheduler/management/commands/scheduler_worker.py
scheduler/migrations/0001_initial_squashed_0005_added_result_ttl.py
scheduler/migrations/0002_alter_cronjob_id_alter_repeatablejob_id_and_more.py
scheduler/migrations/0003_auto_20220329_2107.py
scheduler/migrations/0004_cronjob_at_front_repeatablejob_at_front_and_more.py
scheduler/migrations/0005_alter_cronjob_at_front_alter_repeatablejob_at_front_and_more.py
scheduler/migrations/0006_auto_20230118_1640.py
scheduler/migrations/0007_add_result_ttl.py
scheduler/migrations/0008_rename_str_val_jobarg_val_and_more.py
scheduler/migrations/0009_alter_jobarg_arg_type_alter_jobarg_val_and_more.py
scheduler/migrations/0010_queue.py
scheduler/migrations/0011_worker_alter_queue_options_alter_cronjob_at_front_and_more.py
scheduler/migrations/0012_alter_cronjob_name_alter_repeatablejob_name_and_more.py
scheduler/migrations/0013_alter_cronjob_queue_alter_repeatablejob_queue_and_more.py
scheduler/migrations/0014_alter_cronjob_created_alter_cronjob_modified_and_more.py
scheduler/migrations/0015_rename_cronjob_crontask_and_more.py
scheduler/migrations/0016_rename_jobarg_taskarg_rename_jobkwarg_taskkwarg_and_more.py
django_tasks_scheduler-4.0.8.dist-info/METADATA
django_tasks_scheduler-4.0.8.dist-info/WHEEL
django_tasks_scheduler-4.0.8.dist-info/licenses/LICENSE
django_tasks_scheduler-4.0.8.dist-info/RECORD
