Metadata-Version: 2.4
Name: django-tasks-scheduler
Version: 4.0.8
Summary: An async job scheduler for django using redis/valkey brokers
Project-URL: Homepage, https://github.com/django-commons/django-tasks-scheduler
Project-URL: Documentation, https://django-tasks-scheduler.readthedocs.io/
Project-URL: Bug Tracker, https://github.com/django-commons/django-tasks-scheduler/issues
Project-URL: Funding, https://github.com/sponsors/cunla
Author-email: Daniel Moran <daniel@moransoftware.ca>
Maintainer-email: Daniel Moran <daniel@moransoftware.ca>
License-Expression: MIT
License-File: LICENSE
Keywords: background-jobs,django,job-queue,redis,redis-queue,scheduled-jobs,task-queue,valkey
Classifier: Development Status :: 5 - Production/Stable
Classifier: Environment :: Web Environment
Classifier: Framework :: Django
Classifier: Framework :: Django :: 5.0
Classifier: Framework :: Django :: 5.1
Classifier: Framework :: Django :: 5.2
Classifier: Intended Audience :: Developers
Classifier: License :: OSI Approved :: MIT License
Classifier: Operating System :: OS Independent
Classifier: Programming Language :: Python
Classifier: Programming Language :: Python :: 3.10
Classifier: Programming Language :: Python :: 3.11
Classifier: Programming Language :: Python :: 3.12
Classifier: Programming Language :: Python :: 3.13
Requires-Python: >=3.10
Requires-Dist: click~=8.2
Requires-Dist: croniter>=2.0
Requires-Dist: django>=5
Provides-Extra: sentry
Requires-Dist: sentry-sdk~=2.19; extra == 'sentry'
Provides-Extra: valkey
Requires-Dist: valkey<7,>=6.0.2; extra == 'valkey'
Provides-Extra: yaml
Requires-Dist: pyyaml~=6.0; extra == 'yaml'
Requires-Dist: types-pyyaml>=6.0.12.20250516; extra == 'yaml'
